README.md
setup.py
pyrope/__init__.py
pyrope.egg-info/PKG-INFO
pyrope.egg-info/SOURCES.txt
pyrope.egg-info/dependency_links.txt
pyrope.egg-info/not-zip-safe
pyrope.egg-info/top_level.txt